wconsole_extractor/__init__.py
wconsole_extractor/main.py
wconsole_extractor-1.0.dist-info/LICENSE
wconsole_extractor-1.0.dist-info/METADATA
wconsole_extractor-1.0.dist-info/WHEEL
wconsole_extractor-1.0.dist-info/top_level.txt
wconsole_extractor-1.0.dist-info/RECORD
